clearcut/__init__.py
clearcut/logutils.py
clearcut/otlputils.py
clearcut-0.2.2.post0.dist-info/WHEEL
clearcut-0.2.2.post0.dist-info/METADATA
clearcut-0.2.2.post0.dist-info/RECORD
