Metadata-Version: 2.1
Name: clearcut
Version: 0.2.2.post0
Summary: A straightforward and lightweight logging and tracing library
Home-page: https://github.com/tangibleintelligence/clearcut
License: MIT
Keywords: logging,tracing,opentelemetry
Author: Austin Howard
Author-email: austin@tangibleintelligence.com
Requires-Python: >=3.6,<4.0
Classifier: Development Status :: 4 - Beta
Classifier: Intended Audience :: Developers
Classifier: License :: OSI Approved :: MIT License
Classifier: Programming Language :: Python :: 3
Classifier: Programming Language :: Python :: 3.10
Classifier: Programming Language :: Python :: 3.6
Classifier: Programming Language :: Python :: 3.7
Classifier: Programming Language :: Python :: 3.8
Classifier: Programming Language :: Python :: 3.9
Requires-Dist: more-itertools (>=8.13.0,<9.0.0)
Requires-Dist: opentelemetry-api (>=1.11.1,<2.0.0)
Requires-Dist: opentelemetry-exporter-otlp-proto-http (>=1.11.1,<2.0.0)
Requires-Dist: opentelemetry-instrumentation-logging (>=0.30b1,<0.31)
Requires-Dist: opentelemetry-sdk (>=1.11.1,<2.0.0)
Project-URL: Repository, https://github.com/tangibleintelligence/clearcut
